{
  "updatedAt": "2026-05-31T15:12:08.272Z",
  "totalCount": 4,
  "tags": [
    "Aesthetics",
    "Canvas",
    "Clock",
    "Compilers",
    "Creative Coding",
    "Interactive",
    "JavaScript",
    "Markdown",
    "Neon",
    "Node.js",
    "Widget"
  ],
  "submissions": [
    {
      "folderName": "creating-markdown-parsers-in-nodejs",
      "path": "contributors/creating-markdown-parsers-in-nodejs/index.html",
      "hasIndex": true,
      "author": "Hari Shankar",
      "title": "Creating Markdown Parsers in Node.js",
      "description": "A look at how to build a regex-based lightweight markdown compiler in vanilla JavaScript.",
      "tags": [
        "Node.js",
        "Markdown",
        "JavaScript",
        "Compilers"
      ],
      "github": "hshankar08"
    },
    {
      "folderName": "alex-rivera",
      "path": "contributors/alex-rivera/index.html",
      "hasIndex": true,
      "author": "Alex Rivera",
      "title": "Cyberpunk Neon Clock",
      "description": "A dark themed digital clock with glowing neon aesthetics and interactive visual effects.",
      "tags": [
        "Clock",
        "Neon",
        "Widget",
        "Aesthetics"
      ],
      "github": "alexrivera"
    },
    {
      "folderName": "hshankar08",
      "path": "contributors/hshankar08/index.html",
      "hasIndex": true,
      "author": "Hari Shankar",
      "title": "Doki Doki Waku Waku 3000",
      "description": "Shut up. Baka.",
      "tags": [
        "Interactive"
      ],
      "github": "hshankar08"
    },
    {
      "folderName": "jane-doe",
      "path": "contributors/jane-doe/index.html",
      "hasIndex": true,
      "author": "Jane Doe",
      "title": "Interactive Particle Field",
      "description": "An interactive WebGL-like canvas particle field that reacts to mouse hover and click explosions.",
      "tags": [
        "Canvas",
        "Interactive",
        "Creative Coding"
      ],
      "github": "janedoe"
    }
  ]
}